etc/X11/Xsession.d/85unsettings
unsettings/__init__.py
unsettings/_meta.py
unsettings/about.py
unsettings/backends.py
unsettings/clipboard.py
unsettings/connection.py
unsettings/converter.py
unsettings/dialogs.py
unsettings/i18n.py
unsettings/main.py
unsettings/messages.py
unsettings/optionfile.py
unsettings/settings.py
unsettings/statusbar.py
unsettings/themes.py
unsettings/ui.py
unsettings/widgets.py
unsettings/zgutils.py
unsettings-0.11.data/data/share/applications/unsettings.desktop
unsettings-0.11.data/data/share/locale/ar/LC_MESSAGES/unsettings.mo
unsettings-0.11.data/data/share/locale/bg/LC_MESSAGES/unsettings.mo
unsettings-0.11.data/data/share/locale/cs/LC_MESSAGES/unsettings.mo
unsettings-0.11.data/data/share/locale/de/LC_MESSAGES/unsettings.mo
unsettings-0.11.data/data/share/locale/el/LC_MESSAGES/unsettings.mo
unsettings-0.11.data/data/share/locale/en_GB/LC_MESSAGES/unsettings.mo
unsettings-0.11.data/data/share/locale/es/LC_MESSAGES/unsettings.mo
unsettings-0.11.data/data/share/locale/fi/LC_MESSAGES/unsettings.mo
unsettings-0.11.data/data/share/locale/fr/LC_MESSAGES/unsettings.mo
unsettings-0.11.data/data/share/locale/it/LC_MESSAGES/unsettings.mo
unsettings-0.11.data/data/share/locale/ja/LC_MESSAGES/unsettings.mo
unsettings-0.11.data/data/share/locale/ms/LC_MESSAGES/unsettings.mo
unsettings-0.11.data/data/share/locale/nl/LC_MESSAGES/unsettings.mo
unsettings-0.11.data/data/share/locale/pl/LC_MESSAGES/unsettings.mo
unsettings-0.11.data/data/share/locale/pt_BR/LC_MESSAGES/unsettings.mo
unsettings-0.11.data/data/share/locale/ru/LC_MESSAGES/unsettings.mo
unsettings-0.11.data/data/share/locale/sk/LC_MESSAGES/unsettings.mo
unsettings-0.11.data/data/share/locale/tr/LC_MESSAGES/unsettings.mo
unsettings-0.11.data/data/share/locale/uk/LC_MESSAGES/unsettings.mo
unsettings-0.11.data/data/share/locale/zh_CN/LC_MESSAGES/unsettings.mo
unsettings-0.11.data/data/share/locale/zh_TW/LC_MESSAGES/unsettings.mo
unsettings-0.11.dist-info/DESCRIPTION.rst
unsettings-0.11.dist-info/METADATA
unsettings-0.11.dist-info/RECORD
unsettings-0.11.dist-info/WHEEL
unsettings-0.11.dist-info/entry_points.txt
unsettings-0.11.dist-info/metadata.json
unsettings-0.11.dist-info/top_level.txt
