Metadata-Version: 2.0
Name: unsettings
Version: 0.11
Summary: A configuration frontend for the Unity desktop environment
Home-page: http://www.florian-diesch.de/software/unsettings/
Author: Florian Diesch
Author-email: devel@florian-diesch.de
License: GPLv3
Download-URL: http://www.florian-diesch.de/software/unsettings/
Keywords: Ubuntu,Unity,Configuration,GUI,Frontend
Platform: UNKNOWN
Classifier: Development Status :: 3 - Alpha
Classifier: Environment :: X11 Applications :: Gnome
Classifier: Intended Audience :: End Users/Desktop
Classifier: License :: OSI Approved :: GNU General Public License (GPL)
Classifier: Natural Language :: English
Classifier: Natural Language :: German
Classifier: Operating System :: POSIX :: Linux
Classifier: Programming Language :: Python :: 2.7
Classifier: Topic :: Desktop Environment :: Gnome
Classifier: Topic :: Other/Nonlisted Topic
Classifier: Topic :: Utilities
